Workbook

Sheet 说明
A1: Pibo · 数值系统（bo 经济）— MVP 草案
A3: 用途：这是「数值→毛」「价目/TTU」「有表/无表产出差异」的单一信源。改“参数”页的蓝色旋钮，其余页自动重算。
A5: 【核心原理】Pibo 吃的是“规律与平衡”(=低熵)，不是“越多越好”。所以每个健康指标走“最优区间”曲线，
A6: 而非线性累加：睡好、走够、动得适度 → 长毛快；熬夜、暴走、过劳 = 噪声 → 长毛慢。这条原理同时满足
A7: “符合现实健康科学”和“符合世界观”。文献支撑见“来源”页（步数/睡眠/运动/HRV 均有出处）。
A9: 【货币命名】正式货币 = bo（即 Pibo 头顶的“毛/绒”，长出一根 = 产生一 bo；取自 Pibo 的口头禅“啵”）。全表单位统一为 bo。
A11: 【怎么算 bo = 按数值, 不按天】每日各指标过“评分曲线”得 0–1 分 → 加权×100×恢复乘数 = 当日健康能量；
A12: 能量入池累计，每跨过“每个 bo 所需能量”阈值产生一 bo。于是均衡健康的一天可能长 1.5 个，平庸的一天要两天才攒一个。
A14: 【两条独立的轴（务必分清）】
A15: · 拔毛轴(收没收)：连续3天没拔 → 只有“头顶未拔的 bo（绒毛）”枯萎；不碰已入账 bo 余额、不碰已解锁道具。纯日活/收集机制。
A16: · 健康轴(过没过好)：身体没照顾好(数据差) → Pibo 信号变糊 → 潦草形态 + UI降级。世界观衰减弧，与拔不拔毛无关。
A17: 两条互不干扰：勤拔毛但不健康=潦草但 bo 不枯；健康但懒得拔=清晰但 bo 枯。
... A21: 【数字现状】曲线断点取自文献的“形状与拐点”，绝对取值为可调旋钮；锁定前按真实校准数据微调即可。

Sheet 改动边界
A1: 改动边界 · 哪些该锁 / 哪些边做边调
A2: 一句话：数值系统不该一开始就完全定死。结构先稳、参数边调——而且参数全部走远程配置，避开鸿蒙审核延迟。
A4: 🔒 结构层（先稳，不轻易改） | B4: 为什么不能轻易改
A5: 货币身份：bo = 头顶绒毛，源自健康 | B5: 改了等于换产品语言，用户认知与所有文案/IP重来
A6: 守恒承诺：已得 bo 余额 + 已解锁道具 永不追溯回收 | B6: 这是对用户的承诺，破坏=背叛，再多补偿也救不回信任
A7: 两条轴模型：拔毛轴(收没收) / 健康轴(过没过好) 相互独立 | B7: 模型一改用户彻底糊涂，文案口径全乱
A8: 事件埋点 & 存储 schema：Day1 起全量记录原始事件 | B8: 哪怕公式还没定，也必须先记 raw(步数/睡眠/bo产/bo花/解锁)，否则日后无法回溯重算/重平衡。这是最该“早定”的——不是数字，是仪表盘
A9: 曲线形状原理：睡眠最优U / 步数不惩罚 / 健康永不被罚 | B9: 有科学背书，方向性是契约；改方向=违背现实与世界观
A10: 防通胀架构：阈值累计(非每日固定发) + 存在每日封顶 | B10: “有没有封顶”是结构；“封顶是多少”才是参数
A12: 🎛 参数层（边做边调，远程配置） | B12: 调它安全，本就预期一开始是错的
A13: 每个 bo 所需能量 / 每日能量上限 | B13: 控总产出与防通胀强度
A14: 各评分曲线的断点取值 | B14: 真实用户分布出来后必然要重标定
A15: 道具单价 / TTU 阶梯 | B15: 控解锁节奏
A16: 数据源系数(有表/仅手机/纯App)、信号弱系数 | B16: 控无表用户体验
... A26: 关键指标 | B26: bo 日产分布 / bo 余额随时间(查通胀) / 实际TTU / 无表用户占比与产出 / 衰减触发率 / 道具解锁漏斗

Sheet 参数
A1: 参数（蓝色=可调旋钮 / 远程配置镜像）
A3: 权重（合计应=1） | B3: 值 | C3: 说明
A4: 睡眠权重 | B4: 0.45 | C4: 睡眠权重最高：睡好本身就能撑起“好的一天”，哪怕没运动
A5: 步数权重 | B5: 0.3 | C5: 日常活动量
A6: 运动权重 | B6: 0.25 | C6: 中高强度运动(MVPA)分钟
A7: 权重合计 | B7: =SUM(B4:B6) | C7: 目标 = 1.00（校验）
A9: 能量与货币 | B9: 值 | C9: 说明
A10: 每个 bo 所需能量 | B10: 75 | C10: 能量池每跨过此阈值产生一 bo。调大=更稀缺(防通胀)
A11: 健康能量每日上限 | B11: 110 | C11: 封顶，防“暴走/超长睡”刷毛
A12: App行为能量/日(投入用户) | B12: 10 | C12: 拍照/小游戏/拍一拍彩蛋的期望日产(已封顶)；无健康数据用户的命脉
A14: 数据源系数(#5) | B14: 值 | C14: 说明
A15: 有表/有健康数据 | B15: 1 | C15: 全模型(睡眠+步数+运动+HRV恢复)
A16: 仅手机(无表) | B16: 0.8 | C16: 手机有计步；睡眠近似/手动；无HRV恢复加成 → 打折
A17: 纯App(自评) | B17: 0.55 | C17: 无任何被动数据，靠App行为+自评滑杆；自评低可信，打折更狠
A18: 信号弱剧情系数(可选) | B18: 1 | C18: C方案：无数据时“信号弱,只能勉强收集”。设0.5即开启戏剧化减半，仅作用于纯App列

Sheet 评分曲线
A1: 评分曲线（每个指标 → 0–1 分；断点取自文献，详见“来源”页）
A3: 睡眠(h) | B3: 得分 | D3: 步数 | E3: 得分 | G3: 中高强度运动(min) | H3: 得分 | J3: 恢复状态(0-4) | K3: 乘数 | L3: 说明
A4: 0 | B4: 0 | D4: 0 | E4: 0 | G4: 0 | H4: 0.2 | J4: 0 | K4: 0.85 | L4: 过劳/未恢复(HRV明显低+静息HR升)
A5: 3 | B5: 0.05 | D5: 1000 | E5: 0.12 | G5: 10 | H5: 0.45 | J5: 1 | K5: 0.92 | L5: 轻度疲劳
A6: 4 | B6: 0.14 | D6: 2000 | E6: 0.25 | G6: 15 | H6: 0.6 | J6: 2 | K6: 1 | L6: 正常 / 无数据
A7: 5 | B7: 0.32 | D7: 3000 | E7: 0.38 | G7: 20 | H7: 0.75 | J7: 3 | K7: 1.05 | L7: 恢复较好
A8: 5.5 | B8: 0.46 | D8: 4000 | E8: 0.52 | G8: 30 | H8: 0.92 | J8: 4 | K8: 1.1 | L8: 恢复很好(HRV≥个人基线)
A9: 6 | B9: 0.62 | D9: 5000 | E9: 0.64 | G9: 45 | H9: 1
A10: 6.5 | B10: 0.8 | D10: 6000 | E10: 0.75 | G10: 60 | H10: 1
A11: 7 | B11: 0.93 | D11: 7000 | E11: 0.85 | G11: 75 | H11: 0.98
A12: 7.5 | B12: 1 | D12: 8000 | E12: 0.93 | G12: 90 | H12: 0.95
A13: 8 | B13: 1 | D13: 9000 | E13: 0.97 | G13: 120 | H13: 0.88
A14: 8.5 | B14: 0.82 | D14: 10000 | E14: 1 | G14: 150 | H14: 0.8
A15: 9 | B15: 0.6 | D15: 12000 | E15: 1 | G15: 180 | H15: 0.7
A16: 9.5 | B16: 0.42 | D16: 15000 | E16: 1 | G16: 240 | H16: 0.55
A17: 10 | B17: 0.28 | D17: 20000 | E17: 1
A18: 11 | B18: 0.12
A19: 13 | B19: 0.05
A21: 说明：睡眠为非对称钟形(峰7–8h, 长睡比短睡罚更狠)；步数为饱和曲线(~8–10k封顶, 无惩罚)；
A22: 运动为倒U(最优~30–60min/日, 过量软回落=恢复成本/平衡, 非死亡率硬结论)；恢复乘数由HRV/静息心率判定。
A23: 查表为分段(就近向下取断点)；要更平滑可加密断点。

Sheet 每日能量
A1: 每日能量（示例3档；蓝色=输入, 绿色=跨页公式）
A3: 用户档案 | B3: 睡眠h | C3: 步数 | D3: 运动min | E3: 恢复(0-4) | F3: 睡眠分 | G3: 步数分 | H3: 运动分 | I3: 恢复乘数 | J3: 健康能量 | K3: App能量 | L3: 当日总能量 | M3: 当日≈bo
A4: 健康均衡 | B4: 7.5 | C4: 9000 | D4: 40 | E4: 3 | F4: =LOOKUP(B4,评分曲线!$A$4:$A$19,评分曲线!$B$4:$B$19) | G4: =LOOKUP(C4,评分曲线!$D$4:$D$17,评分曲线!$E$4:$E$17) | H4: =LOOKUP(D4,评分曲线!$G$4:$G$16,评分曲线!$H$4:$H$16) | I4: =LOOKUP(E4,评分曲线!$J$4:$J$8,评分曲线!$K$4:$K$8) | J4: =MIN(参数!$B$11,(F4*参数!$B$4+G4*参数!$B$5+H4*参数!$B$6)*100*I4) | K4: =参数!$B$12 | L4: =J4+K4 | M4: =L4/参数!$B$10
A5: 普通 | B5: 6.5 | C5: 5000 | D5: 15 | E5: 2 | F5: =LOOKUP(B5,评分曲线!$A$4:$A$19,评分曲线!$B$4:$B$19) | G5: =LOOKUP(C5,评分曲线!$D$4:$D$17,评分曲线!$E$4:$E$17) | H5: =LOOKUP(D5,评分曲线!$G$4:$G$16,评分曲线!$H$4:$H$16) | I5: =LOOKUP(E5,评分曲线!$J$4:$J$8,评分曲线!$K$4:$K$8) | J5: =MIN(参数!$B$11,(F5*参数!$B$4+G5*参数!$B$5+H5*参数!$B$6)*100*I5) | K5: =参数!$B$12 | L5: =J5+K5 | M5: =L5/参数!$B$10
A6: 久坐 | B6: 5.5 | C6: 2500 | D6: 0 | E6: 1 | F6: =LOOKUP(B6,评分曲线!$A$4:$A$19,评分曲线!$B$4:$B$19) | G6: =LOOKUP(C6,评分曲线!$D$4:$D$17,评分曲线!$E$4:$E$17) | H6: =LOOKUP(D6,评分曲线!$G$4:$G$16,评分曲线!$H$4:$H$16) | I6: =LOOKUP(E6,评分曲线!$J$4:$J$8,评分曲线!$K$4:$K$8) | J6: =MIN(参数!$B$11,(F6*参数!$B$4+G6*参数!$B$5+H6*参数!$B$6)*100*I6) | K6: =参数!$B$12 | L6: =J6+K6 | M6: =L6/参数!$B$10
A8: 健康能量 = MIN(上限, (睡眠分×w睡+步数分×w步+运动分×w运)×100×恢复乘数)。可改输入即时看变化。

Sheet 产出差异
A1: 产出差异 · 有表 / 无表（bo 每周）
A3: 用户档案 | B3: 有表(bo/周) | C3: 仅手机(bo/周) | D3: 纯App(bo/周)
A4: =每日能量!A4 | B4: =((每日能量!J4*参数!$B$15+每日能量!K4)*7)/参数!$B$10 | C4: =((每日能量!J4*参数!$B$16+每日能量!K4)*7)/参数!$B$10 | D4: =((每日能量!J4*参数!$B$17+每日能量!K4)*参数!$B$18*7)/参数!$B$10
A5: =每日能量!A5 | B5: =((每日能量!J5*参数!$B$15+每日能量!K5)*7)/参数!$B$10 | C5: =((每日能量!J5*参数!$B$16+每日能量!K5)*7)/参数!$B$10 | D5: =((每日能量!J5*参数!$B$17+每日能量!K5)*参数!$B$18*7)/参数!$B$10
A6: =每日能量!A6 | B6: =((每日能量!J6*参数!$B$15+每日能量!K6)*7)/参数!$B$10 | C6: =((每日能量!J6*参数!$B$16+每日能量!K6)*7)/参数!$B$10 | D6: =((每日能量!J6*参数!$B$17+每日能量!K6)*参数!$B$18*7)/参数!$B$10
A8: 读法：同一个人，没表只是产出打折(仍能玩、仍能赚)，而不是被锁死。
A9: 建议组合：A手机兜底 + C剧情化降级 打底, B行为补充, 不上硬门槛(见“说明/对话”)。

Sheet 价目与TTU
A1: 道具价目 & 全解锁天数(TTU) · 线性解锁(MVP)
A3: 道具 | B3: 单价(bo) | C3: 累计(bo) | D3: 健康用户(周) | E3: 普通用户(周) | F3: 久坐用户(周)
A4: 道具1·灯 | B4: 2 | C4: =B4 | D4: =IFERROR(C4/产出差异!$B$4,"-") | E4: =IFERROR(C4/产出差异!$B$5,"-") | F4: =IFERROR(C4/产出差异!$B$6,"-")
A5: 道具2·桌子 | B5: 4 | C5: =C4+B5 | D5: =IFERROR(C5/产出差异!$B$4,"-") | E5: =IFERROR(C5/产出差异!$B$5,"-") | F5: =IFERROR(C5/产出差异!$B$6,"-")
A6: 道具3·地毯 | B6: 5 | C6: =C5+B6 | D6: =IFERROR(C6/产出差异!$B$4,"-") | E6: =IFERROR(C6/产出差异!$B$5,"-") | F6: =IFERROR(C6/产出差异!$B$6,"-")
A7: 道具4·窗 | B7: 5 | C7: =C6+B7 | D7: =IFERROR(C7/产出差异!$B$4,"-") | E7: =IFERROR(C7/产出差异!$B$5,"-") | F7: =IFERROR(C7/产出差异!$B$6,"-")
A8: 道具5·画 | B8: 6 | C8: =C7+B8 | D8: =IFERROR(C8/产出差异!$B$4,"-") | E8: =IFERROR(C8/产出差异!$B$5,"-") | F8: =IFERROR(C8/产出差异!$B$6,"-")
A9: 全部解锁 | B9: =SUM(B4:B8) | C9: =C8 | D9: =IFERROR(C8/产出差异!$B$4,"-") | E9: =IFERROR(C8/产出差异!$B$5,"-") | F9: =IFERROR(C8/产出差异!$B$6,"-")
A11: 调价目标：首件第1–2天(尝甜头)，健康用户~2周全解锁。改单价或“参数”即时重算。
A12: 后期商店化：单价改目录配置即可(货币不变)；须加轮换/消耗型sink，避免解锁完后 bo 失去意义。

Sheet 节律奖励
A1: 节律奖励 · 规律的量化（问题2）
A2: 原则：奖励“跨天一致性”，不奖单日猛；只加分不扣分（不规律=拿不到bonus，倍率永不<1）；宽容（滚动14天窗+缓慢滚出，无连击清零）。
A4: 参数（蓝=可调） | B4: 值 | C4: 说明
A5: 滚动窗口(天) | B5: 14 | C5: 越长越宽容、越奖励持续规律
A6: 睡眠节律权重 | B6: 0.45 | C6: 文献:睡眠规律性>时长
A7: 活动节律权重 | B7: 0.3
A8: 出勤权重 | B8: 0.25
A9: 睡眠中点SD-优(min) | B9: 30 | C9: ≤此值=满分
A10: 睡眠中点SD-差(min) | B10: 120 | C10: ≥此值=0分
A11: 步数CV-优 | B11: 0.25 | C11: ≤此值=满分
A12: 步数CV-差 | B12: 0.75 | C12: ≥此值=0分
A13: 出勤达标·日能量门槛 | B13: 40 | C13: 当日健康能量≥此值算达标
A14: bo日倍率·上限加成 | B14: 0.5 | C14: 倍率=1.00~1.50
A15: 每周节律奖励上限(bo) | B15: 8 | C15: 周报发放
A16: 权重合计校验 | B16: =B6+B7+B8 | C16: 应=1.00
A18: 用户档案 | B18: 睡眠中点SD(min) | C18: 步数CV | D18: 窗内达标天 | E18: 睡眠节律R | F18: 活动节律R | G18: 出勤R | H18: 节律分(0-100) | I18: bo日倍率 | J18: 每周奖励(bo)
A19: 规律健康者 | B19: 25 | C19: 0.2 | D19: 13 | E19: =MAX(0,MIN(1,($B$10-B19)/($B$10-$B$9))) | F19: =MAX(0,MIN(1,($B$12-C19)/($B$12-$B$11))) | G19: =D19/$B$5 | H19: =(E19*$B$6+F19*$B$7+G19*$B$8)*100 | I19: =1+$B$14*(H19/100) | J19: =ROUND($B$15*(H19/100),0)
A20: 普通波动者 | B20: 70 | C20: 0.5 | D20: 8 | E20: =MAX(0,MIN(1,($B$10-B20)/($B$10-$B$9))) | F20: =MAX(0,MIN(1,($B$12-C20)/($B$12-$B$11))) | G20: =D20/$B$5 | H20: =(E20*$B$6+F20*$B$7+G20*$B$8)*100 | I20: =1+$B$14*(H20/100) | J20: =ROUND($B$15*(H20/100),0)
A21: 极不规律 | B21: 130 | C21: 0.9 | D21: 3 | E21: =MAX(0,MIN(1,($B$10-B21)/($B$10-$B$9))) | F21: =MAX(0,MIN(1,($B$12-C21)/($B$12-$B$11))) | G21: =D21/$B$5 | H21: =(E21*$B$6+F21*$B$7+G21*$B$8)*100 | I21: =1+$B$14*(H21/100) | J21: =ROUND($B$15*(H21/100),0)
A23: 发放（两通道，都在当前 bo 经济内）：① bo日倍率 乘到「每日能量」算出的当日 bo（1.00–1.50，永不<1）；② 每周节律奖励在周报发放。
A24: 综合产出 ≈ 产出差异(每周) × bo日倍率 + 每周节律奖励。
A25: 睡眠节律=睡眠中点SD（越小越规律）；活动节律=日步数CV；出勤=窗内日能量≥门槛的天数÷窗口。
A26: 数据不足：窗内有效睡眠夜过少→睡眠节律按中性0.5(不惩罚)；mean步数=0→活动节律按中性。进阶可换学界 SRI 指数。
A27: 反焦虑：滚动窗+缓慢滚出，断一两天只小幅下降，绝无“连击清零”。

Sheet 来源
A1: 文献来源（曲线断点依据）
A3: 指标 | B3: 结论(用于曲线) | C3: 出处
A4: 步数 | B4: 死亡率随步数下降, ~8,000步封顶(<60岁8–10k, ≥60岁6–8k); “1万步”无强证据; 走多不有害只是趋平 | C4: Paluch et al. 2022, Lancet Public Health, 15-cohort meta-analysis — https://pmc.ncbi.nlm.nih.gov/articles/PMC9289978/
A5: 睡眠 | B5: U型, 最优~7h; 短睡每−1h风险×1.06, 长睡每+1h风险×1.13(长睡罚更狠) | C5: Sleep duration & all-cause mortality meta-analyses — https://pmc.ncbi.nlm.nih.gov/articles/PMC2864873/ ; https://www.ahajournals.org/doi/10.1161/JAHA.117.005947
A6: 睡眠规律 | B6: 睡眠“规律性”比时长更能预测死亡率(印证“Pibo吃规律”) | C6: Windred et al. 2024, SLEEP — https://academic.oup.com/sleep/article/47/1/zsad253/7280269
A7: 运动 | B7: WHO: 150–300min/周中等(或75–150min/周高强度); 收益~300min/周后趋平, 2–4倍仍微益, 极端非明显有害 | C7: WHO 2020 Guidelines — https://pmc.ncbi.nlm.nih.gov/articles/PMC7719906/ ; AHA 150–600min — https://newsroom.heart.org/news/new-study-finds-lowest-risk-of-death-was-among-adults-who-exercised-150-600-minutesweek
A8: HRV/静息心率 | B8: HRV越高/越接近个人基线越好(健康均值~42ms); 低HRV↔疾病; 用作恢复门控/过劳信号 | C8: WebMD HRV overview — https://www.webmd.com/heart/what-is-heart-rate-variability ; HRV & longevity — https://www.ncbi.nlm.nih.gov/pmc/articles/PMC7527628/
A10: 注：曲线取文献“形状与拐点”；绝对分值为可调旋钮, 锁定前按真实校准数据微调。
